{
  "_fv": 24,
  "_type": "recipe",
  "definition": {
    "recipeType": "Crafting",
    "xpReward": 0.0,
    "cookingTime": 200,
    "recipeRetstackSize": 9,
    "group": "cyan_shard",
    "recipeShapeless": true,
    "recipeSlots": [
      {
        "value": ""
      },
      {
        "value": ""
      },
      {
        "value": ""
      },
      {
        "value": ""
      },
      {
        "value": "CUSTOM:CyanShardBlock"
      },
      {
        "value": ""
      },
      {
        "value": ""
      },
      {
        "value": ""
      },
      {
        "value": ""
      }
    ],
    "recipeReturnStack": {
      "value": "CUSTOM:CyanGem"
    },
    "name": "cyan_block_to_shards",
    "namespace": "mod"
  }
}